reciprocalspaceship/VERSION
reciprocalspaceship/__init__.py
reciprocalspaceship/concat.py
reciprocalspaceship/dataseries.py
reciprocalspaceship/dataset.py
reciprocalspaceship/decorators.py
reciprocalspaceship/algorithms/__init__.py
reciprocalspaceship/algorithms/intensity.py
reciprocalspaceship/algorithms/merge.py
reciprocalspaceship/algorithms/scale_merged_intensities.py
reciprocalspaceship/commandline/__init__.py
reciprocalspaceship/commandline/cifdump.py
reciprocalspaceship/commandline/mtzdump.py
reciprocalspaceship/dtypes/__init__.py
reciprocalspaceship/dtypes/base.py
reciprocalspaceship/dtypes/floating.py
reciprocalspaceship/dtypes/inference.py
reciprocalspaceship/dtypes/integer.py
reciprocalspaceship/dtypes/internals.py
reciprocalspaceship/dtypes/summarize.py
reciprocalspaceship/io/__init__.py
reciprocalspaceship/io/ccp4map.py
reciprocalspaceship/io/common.py
reciprocalspaceship/io/crystfel.py
reciprocalspaceship/io/csv.py
reciprocalspaceship/io/dials.py
reciprocalspaceship/io/dials_mpi.py
reciprocalspaceship/io/mtz.py
reciprocalspaceship/io/pickle.py
reciprocalspaceship/io/precognition.py
reciprocalspaceship/stats/__init__.py
reciprocalspaceship/stats/completeness.py
reciprocalspaceship/utils/__init__.py
reciprocalspaceship/utils/asu.py
reciprocalspaceship/utils/binning.py
reciprocalspaceship/utils/cell.py
reciprocalspaceship/utils/grid.py
reciprocalspaceship/utils/math.py
reciprocalspaceship/utils/phases.py
reciprocalspaceship/utils/rfree.py
reciprocalspaceship/utils/stats.py
reciprocalspaceship/utils/structurefactors.py
reciprocalspaceship/utils/symmetry.py
reciprocalspaceship/utils/units.py
reciprocalspaceship-1.0.7.dist-info/licenses/LICENSE
tests/__init__.py
tests/conftest.py
tests/test_dataseries.py
tests/test_dataset.py
tests/test_dataset_anomalous.py
tests/test_dataset_binning.py
tests/test_dataset_grid.py
tests/test_dataset_index.py
tests/test_dataset_preserve_attributes.py
tests/test_dataset_signatures.py
tests/test_dataset_symops.py
tests/test_decorators.py
tests/test_summarize_mtz_dtypes.py
reciprocalspaceship-1.0.7.dist-info/METADATA
reciprocalspaceship-1.0.7.dist-info/WHEEL
reciprocalspaceship-1.0.7.dist-info/entry_points.txt
reciprocalspaceship-1.0.7.dist-info/top_level.txt
reciprocalspaceship-1.0.7.dist-info/RECORD
