Metadata-Version: 2.4
Name: reciprocalspaceship
Version: 1.0.7
Summary: Tools for exploring reciprocal space
Home-page: https://rs-station.github.io/reciprocalspaceship/
Author: Kevin M. Dalton, Jack B. Greisman
Author-email: kmdalton@g.harvard.edu, greisman@g.harvard.edu
License: MIT
Project-URL: Bug Tracker, https://github.com/rs-station/reciprocalspaceship/issues
Project-URL: Documentation, https://rs-station.github.io/reciprocalspaceship/
Project-URL: Source Code, https://github.com/rs-station/reciprocalspaceship
Classifier: Development Status :: 3 - Alpha
Classifier: Intended Audience :: Developers
Classifier: Intended Audience :: Science/Research
Classifier: License :: OSI Approved :: MIT License
Classifier: Topic :: Scientific/Engineering :: Chemistry
Classifier: Topic :: Scientific/Engineering :: Physics
Classifier: Topic :: Software Development :: Libraries :: Python Modules
Classifier: Programming Language :: Python
Requires-Python: >=3.9
License-File: LICENSE
Requires-Dist: gemmi<=0.7.3,>=0.7.0
Requires-Dist: pandas<=2.3.3,>=2.2.2
Requires-Dist: numpy
Requires-Dist: scipy
Requires-Dist: ipython
Requires-Dist: msgpack
Requires-Dist: setuptools
Requires-Dist: joblib
Provides-Extra: dev
Requires-Dist: pytest; extra == "dev"
Requires-Dist: pytest-cov; extra == "dev"
Requires-Dist: pytest-xdist; extra == "dev"
Provides-Extra: doc
Requires-Dist: sphinx; extra == "doc"
Requires-Dist: sphinx_rtd_theme; extra == "doc"
Requires-Dist: nbsphinx; extra == "doc"
Requires-Dist: sphinx-design; extra == "doc"
Requires-Dist: sphinxcontrib-autoprogram; extra == "doc"
Requires-Dist: autodocsumm; extra == "doc"
Requires-Dist: jupyter; extra == "doc"
Requires-Dist: tqdm; extra == "doc"
Requires-Dist: matplotlib; extra == "doc"
Requires-Dist: seaborn; extra == "doc"
Requires-Dist: celluloid; extra == "doc"
Requires-Dist: scikit-image; extra == "doc"
Provides-Extra: examples
Requires-Dist: jupyter; extra == "examples"
Requires-Dist: tqdm; extra == "examples"
Requires-Dist: matplotlib; extra == "examples"
Requires-Dist: seaborn; extra == "examples"
Requires-Dist: celluloid; extra == "examples"
Requires-Dist: scikit-image; extra == "examples"
Dynamic: author
Dynamic: author-email
Dynamic: classifier
Dynamic: description
Dynamic: home-page
Dynamic: license
Dynamic: license-file
Dynamic: project-url
Dynamic: provides-extra
Dynamic: requires-dist
Dynamic: requires-python
Dynamic: summary
